kittenmedia/__init__.py
kittenmedia/kmedia.py
kittenmedia-0.1.1.dist-info/LICENSE
kittenmedia-0.1.1.dist-info/METADATA
kittenmedia-0.1.1.dist-info/WHEEL
kittenmedia-0.1.1.dist-info/top_level.txt
kittenmedia-0.1.1.dist-info/RECORD
